momlib/__init__.py
momlib/_errors.py
momlib/_linalg.py
momlib/_matrix.py
momlib/_vector.py
momlib-0.0.9.dist-info/LICENSE.md
momlib-0.0.9.dist-info/METADATA
momlib-0.0.9.dist-info/WHEEL
momlib-0.0.9.dist-info/top_level.txt
momlib-0.0.9.dist-info/RECORD
