Metadata-Version: 2.1
Name: momlib
Version: 0.0.9
Summary: Mathematical Object Manipulation Library
Home-page: https://github.com/B-Roux/momlib
Author: B. Roux
License: BSD (3-Clause)
Project-URL: Bug Tracker, https://github.com/B-Roux/momlib/issues
Keywords: library,vector,matrix,mathematics
Classifier: Development Status :: 3 - Alpha
Classifier: Intended Audience :: Developers
Classifier: License :: OSI Approved :: BSD License
Classifier: Operating System :: OS Independent
Classifier: Programming Language :: Python :: 3.10
Classifier: Programming Language :: Python :: 3.11
Requires-Python: >=3.10
License-File: LICENSE.md
